graphdisplay/__init__.py
graphdisplay/graphdisplay.py
graphdisplay-0.0.3.dist-info/METADATA
graphdisplay-0.0.3.dist-info/WHEEL
graphdisplay-0.0.3.dist-info/top_level.txt
graphdisplay-0.0.3.dist-info/RECORD
