Metadata-Version: 2.1
Name: graphdisplay
Version: 0.0.3
Summary: Librería para representar visualmente grafos de tipo diccionario
Home-page: https://github.com/seniorbeto
Author: Alberto Penas Díaz
Author-email: albertopenasdiaz@gmail.com
License: MIT
Requires-Dist: tk
